MANIFEST.in
README.rst
setup.py
env/lib/python2.7/site-packages/flask/testsuite/static/index.html
env/lib/python2.7/site-packages/flask/testsuite/templates/_macro.html
env/lib/python2.7/site-packages/flask/testsuite/templates/context_template.html
env/lib/python2.7/site-packages/flask/testsuite/templates/escaping_template.html
env/lib/python2.7/site-packages/flask/testsuite/templates/simple_template.html
env/lib/python2.7/site-packages/flask/testsuite/templates/template_filter.html
env/lib/python2.7/site-packages/flask/testsuite/templates/template_test.html
env/lib/python2.7/site-packages/flask/testsuite/test_apps/blueprintapp/apps/admin/static/css/test.css
env/lib/python2.7/site-packages/flask/testsuite/test_apps/blueprintapp/apps/admin/templates/admin/index.html
env/lib/python2.7/site-packages/flask/testsuite/test_apps/blueprintapp/apps/frontend/templates/frontend/index.html
env/lib/python2.7/site-packages/flask/testsuite/test_apps/moduleapp/apps/admin/static/css/test.css
env/lib/python2.7/site-packages/flask/testsuite/test_apps/moduleapp/apps/admin/templates/index.html
env/lib/python2.7/site-packages/flask/testsuite/test_apps/moduleapp/apps/frontend/templates/index.html
env/lib/python2.7/site-packages/jinja2/testsuite/res/templates/broken.html
env/lib/python2.7/site-packages/jinja2/testsuite/res/templates/syntaxerror.html
env/lib/python2.7/site-packages/jinja2/testsuite/res/templates/test.html
env/lib/python2.7/site-packages/jinja2/testsuite/res/templates/foo/test.html
env/lib/python2.7/site-packages/werkzeug/debug/shared/debugger.js
env/lib/python2.7/site-packages/werkzeug/debug/shared/jquery.js
env/lib/python2.7/site-packages/werkzeug/debug/shared/style.css
habits/__init__.py
habits/api.py
habits/config.py
habits/server.py
habits.egg-info/PKG-INFO
habits.egg-info/SOURCES.txt
habits.egg-info/dependency_links.txt
habits.egg-info/entry_points.txt
habits.egg-info/requires.txt
habits.egg-info/top_level.txt
habits/static/app.html
habits/static/components/bootstrap/dist/css/bootstrap-theme.css
habits/static/components/bootstrap/dist/css/bootstrap-theme.min.css
habits/static/components/bootstrap/dist/css/bootstrap.css
