Metadata-Version: 1.0
Name: habits
Version: 0.0.16
Summary: A lightweight habit tracker with a simple REST API.
Home-page: http://github.com/csu/habits
Author: Christopher Su
Author-email: chris+gh@christopher.su
License: GPL v3
Keywords: habits,quantified self,data,api
Platform: UNKNOWN
